rofipaste/__init__.py
rofipaste/cli.py
rofipaste/rofipaste.py
rofipaste-0.1.8.dist-info/AUTHORS.rst
rofipaste-0.1.8.dist-info/LICENSE
rofipaste-0.1.8.dist-info/METADATA
rofipaste-0.1.8.dist-info/WHEEL
rofipaste-0.1.8.dist-info/entry_points.txt
rofipaste-0.1.8.dist-info/top_level.txt
rofipaste-0.1.8.dist-info/RECORD
