Metadata-Version: 2.1
Name: rofipaste
Version: 0.1.8
Summary: A tool to paste some useful things
Home-page: https://github.com/Any0ne22/rofipaste
Author: Tom GOUVILLE
Author-email: tom.gouville@telecomnancy.net
License: GNU General Public License v3
Keywords: rofipaste
Platform: UNKNOWN
Classifier: Development Status :: 2 - Pre-Alpha
Classifier: Intended Audience :: Developers
Classifier: License :: OSI Approved :: GNU General Public License v3 (GPLv3)
Classifier: Natural Language :: English
Classifier: Programming Language :: Python :: 3.7
Classifier: Programming Language :: Python :: 3.8
Requires-Python: >=3.7
Requires-Dist: Click (>=7.0)
Requires-Dist: click-config-file (>=0.6.0)
Requires-Dist: pyxdg (>=0.26)
